{
  "resourceType": "ClinicalUseDefinition",
  "id": "DB00391-21287",
  "meta": {
    "profile": [
      "http://hl7.org/fhir/StructureDefinition/ClinicalUseDefinition"
    ],
    "lastUpdated": "2026-03-09T14:20:53.717374+00:00"
  },
  "type": "indication",
  "subject": [
    {
      "reference": "MedicationKnowledge/DB00391",
      "display": "Sulpiride ERC 50 mg, capsules"
    }
  ],
  "indication": {
    "diseaseSymptomProcedure": {
      "coding": [
        {
          "system": "http://purl.obolibrary.org/obo/mondo.owl",
          "code": "21287",
          "display": "carcinoma in situ of epiglottis"
        }
      ],
      "text": "carcinoma in situ of epiglottis"
    }
  },
  "extension": [
    {
      "url": "https://nltxgnn.yao.care/fhir/StructureDefinition/prediction-source",
      "valueString": "TxGNN-KG"
    },
    {
      "url": "https://nltxgnn.yao.care/fhir/StructureDefinition/research-only",
      "valueBoolean": true
    }
  ]
}