{
  "resourceType": "MedicationKnowledge",
  "id": "DB01339",
  "meta": {
    "profile": [
      "http://hl7.org/fhir/StructureDefinition/MedicationKnowledge"
    ],
    "lastUpdated": "2026-03-09T14:20:04.709970+00:00"
  },
  "code": {
    "coding": [
      {
        "system": "https://www.drugbank.ca",
        "code": "DB01339",
        "display": "Vecuronium SUN 10 mg poeder voor oplossing voor injectie en intraveneuze infusie"
      }
    ],
    "text": "Vecuronium SUN 10 mg poeder voor oplossing voor injectie en intraveneuze infusie"
  },
  "status": "active",
  "manufacturer": {
    "display": "Various"
  },
  "jurisdiction": [
    {
      "coding": [
        {
          "system": "urn:iso:std:iso:3166",
          "code": "Nl",
          "display": "Netherlands"
        }
      ]
    }
  ]
}